{"url":"https://www.anapioficeandfire.com/api/characters/867","name":"Rhaegar Targaryen","gender":"Male","culture":"Valyrian","born":"In 259 AC, at Summerhall","died":"In 283 AC, at the Trident","titles":["Prince of Dragonstone","Ser"],"aliases":["Silver Prince","The Dragon Prince","The Last Dragon"],"father":"","mother":"","spouse":"https://www.anapioficeandfire.com/api/characters/361","allegiances":["https://www.anapioficeandfire.com/api/houses/378"],"books":["https://www.anapioficeandfire.com/api/books/1","https://www.anapioficeandfire.com/api/books/2","https://www.anapioficeandfire.com/api/books/3","https://www.anapioficeandfire.com/api/books/5","https://www.anapioficeandfire.com/api/books/8"],"povBooks":[],"tvSeries":[""],"playedBy":[""]}