{"url":"https://www.anapioficeandfire.com/api/houses/118","name":"House Estren of Wyndhall","region":"The Westerlands","coatOfArms":"A green saltire between four red double-headed eagles, on a white field(Argent, a saltire vert between four double-headed eagles displayed gules)","words":"","titles":["Lord of Wyndhall"],"seats":["Wyndhall"],"currentLord":"https://www.anapioficeandfire.com/api/characters/860","heir":"","overlord":"https://www.anapioficeandfire.com/api/houses/229","founded":"","founder":"","diedOut":"","ancestralWeapons":[""],"cadetBranches":[],"swornMembers":["https://www.anapioficeandfire.com/api/characters/860"]}